topsisGod.py
topsisGod-1.0.0.dist-info/LICENSE.txt
topsisGod-1.0.0.dist-info/METADATA
topsisGod-1.0.0.dist-info/WHEEL
topsisGod-1.0.0.dist-info/top_level.txt
topsisGod-1.0.0.dist-info/RECORD
