Metadata-Version: 2.1
Name: topsisGod
Version: 1.0.0
Summary: Calculation of Topsis Score
Home-page: UNKNOWN
Author: Sahil Chhabra
Author-email: sahil.chh718@gmail.com
License: UNKNOWN
Platform: UNKNOWN
Classifier: Operating System :: OS Independent
